setup.cfg
setup.py
franz_mosaic/__init__.py
franz_mosaic/app.py
franz_mosaic.egg-info/PKG-INFO
franz_mosaic.egg-info/SOURCES.txt
franz_mosaic.egg-info/dependency_links.txt
franz_mosaic.egg-info/entry_points.txt
franz_mosaic.egg-info/requires.txt
franz_mosaic.egg-info/top_level.txt