Metadata-Version: 1.1
Name: franz-mosaic
Version: 1.2
Summary: reduces pictures and creates new image based on reduced information
Home-page: https://github.com/kingmray/franz_mosaic
Author: raymond schmidt
Author-email: raymond.schmidt@googlemail.com
License: UNKNOWN
Download-URL: https://github.com/kingmray/franz_mosaic/archive/v1.0.2.tar.gz
Keywords: image,processing
Platform: UNKNOWN
